Metadata-Version: 2.1
Name: odoo-addon-website_menu_by_user_status
Version: 18.0.1.0.0.2
Requires-Python: >=3.10
Requires-Dist: odoo==18.0.*
Summary: Allow to manage the display of website.menus
Home-page: https://github.com/OCA/website
License: AGPL-3
Author: Savoir-faire Linux,Odoo Community Association (OCA)
Author-email: support@odoo-community.org
Classifier: Programming Language :: Python
Classifier: Framework :: Odoo
Classifier: Framework :: Odoo :: 18.0
Classifier: License :: OSI Approved :: GNU Affero General Public License v3
